LICENSE
README.md
setup.cfg
setup.py
pacheco_core.egg-info/PKG-INFO
pacheco_core.egg-info/SOURCES.txt
pacheco_core.egg-info/dependency_links.txt
pacheco_core.egg-info/requires.txt
pacheco_core.egg-info/top_level.txt
retico_core/version.py